extractcontent3/__init__.py
extractcontent3/extractcontent3.py
extractcontent3-0.0.2.dist-info/DESCRIPTION.rst
extractcontent3-0.0.2.dist-info/METADATA
extractcontent3-0.0.2.dist-info/RECORD
extractcontent3-0.0.2.dist-info/WHEEL
extractcontent3-0.0.2.dist-info/metadata.json
extractcontent3-0.0.2.dist-info/top_level.txt
