Metadata-Version: 2.0
Name: extractcontent3
Version: 0.0.2
Summary: ExtractContent for Python 3
Home-page: https://github.com/kanjirz50/python-extractcontent3
Author: UNKNOWN
Author-email: UNKNOWN
License: BSD 2-Clause
Platform: UNKNOWN
Classifier: Development Status :: 3 - Alpha
Classifier: License :: OSI Approved :: BSD License
Classifier: Programming Language :: Python :: 3.6
Requires-Python: ~=3.3
